thinkcache/__init__.py
thinkcache/cache.py
thinkcache/config.py
thinkcache/utils.py
thinkcache-0.1.2.dist-info/METADATA
thinkcache-0.1.2.dist-info/WHEEL
thinkcache-0.1.2.dist-info/top_level.txt
thinkcache-0.1.2.dist-info/RECORD
