Metadata-Version: 2.4
Name: thinkcache
Version: 0.1.2
Summary: A high-performance semantic caching system with FAISS vector similarity search for LLMs
Home-page: https://github.com/Chrisolande/langchain-semantic-cache
Author: Chris Olande
Author-email: Chris Olande <olandechris@gmail.com>
License: MIT
Project-URL: homepage, https://github.com/Chrisolande/thinkcache
Project-URL: documentation, https://github.com/Chrisolande/thinkcache#readme
Project-URL: bug_reports, https://github.com/Chrisolande/thinkcache/issues
Project-URL: source, https://github.com/Chrisolande/thinkcache
Keywords: semantic,cache,faiss,vector,similarity,llm,ai,ml
Classifier: Development Status :: 3 - Alpha
Classifier: Intended Audience :: Developers
Classifier: License :: OSI Approved :: MIT License
Classifier: Operating System :: OS Independent
Classifier: Programming Language :: Python :: 3
Classifier: Programming Language :: Python :: 3.8
Classifier: Programming Language :: Python :: 3.9
Classifier: Programming Language :: Python :: 3.10
Classifier: Programming Language :: Python :: 3.11
Classifier: Programming Language :: Python :: 3.12
Classifier: Topic :: Software Development :: Libraries :: Python Modules
Classifier: Topic :: Scientific/Engineering :: Artificial Intelligence
Classifier: Topic :: Database
Classifier: Topic :: Internet :: WWW/HTTP :: Indexing/Search
Requires-Python: >=3.8
Requires-Dist: langchain>=0.1.0
Requires-Dist: langchain-community>=0.0.10
Requires-Dist: langchain-huggingface>=0.0.1
Requires-Dist: faiss-cpu>=1.7.0
Requires-Dist: numpy>=1.20.0
Requires-Dist: sentence-transformers>=2.0.0
Provides-Extra: dev
Requires-Dist: pytest>=7.0.0; extra == "dev"
Requires-Dist: pytest-asyncio>=0.21.0; extra == "dev"
Requires-Dist: black>=22.0.0; extra == "dev"
Requires-Dist: flake8>=4.0.0; extra == "dev"
Requires-Dist: mypy>=0.950; extra == "dev"
Requires-Dist: pre-commit>=2.20.0; extra == "dev"
Provides-Extra: quantization
Requires-Dist: faiss-gpu>=1.7.0; extra == "quantization"
Dynamic: author
Dynamic: home-page
Dynamic: requires-python
